emirdrp/__init__.py
emirdrp/_version.py
emirdrp/conftest.py
emirdrp/datamodel.py
emirdrp/decorators.py
emirdrp/drp.yaml
emirdrp/loader.py
emirdrp/preprocess.py
emirdrp/products.py
emirdrp/requirements.py
emirdrp/core/__init__.py
emirdrp/core/correctors.py
emirdrp/core/extra.py
emirdrp/core/recipe.py
emirdrp/core/utils.py
emirdrp/core/tests/__init__.py
emirdrp/core/tests/test_utils.py
emirdrp/instrument/__init__.py
emirdrp/instrument/channels.py
emirdrp/instrument/csu_configuration.py
emirdrp/instrument/csuconf.py
emirdrp/instrument/distortions.py
emirdrp/instrument/components/__init__.py
emirdrp/instrument/components/csu.py
emirdrp/instrument/components/dtu.py
emirdrp/instrument/components/dtuaxis.py
emirdrp/instrument/components/tests/__init__.py
emirdrp/instrument/components/tests/test_dtu.py
emirdrp/instrument/components/tests/test_dtuaxis.py
emirdrp/instrument/components/tests/test_dtudev.py
emirdrp/instrument/configs/Oliva_etal_2013.dat
emirdrp/instrument/configs/__init__.py
emirdrp/instrument/configs/bars_nominal_positions_test.txt
emirdrp/instrument/configs/component-1ac26dff-4c3f-43d8-a069-7470357120d6.json
emirdrp/instrument/configs/component-5dcdda56-3a5f-4bb8-b88c-776f7eee6cfe.json
emirdrp/instrument/configs/component-82b66c4d-e0c7-4395-9cea-c7cd753a5c06.json
emirdrp/instrument/configs/component-bc90ac77-2fd4-47c0-97ff-88a278a12785.json
emirdrp/instrument/configs/instrument-225fcaf2-7f6f-49cc-972a-70fd0aee8e96.json
emirdrp/instrument/configs/instrument-443fc0d1-e09a-48cc-a0fd-02be6f399da2.json
emirdrp/instrument/configs/lines_argon_neon_xenon_empirical.dat
emirdrp/instrument/configs/lines_argon_neon_xenon_empirical_LR.dat
emirdrp/instrument/configs/setup-715c7ced-f989-42a6-bb74-a5b5cda0495c.json
emirdrp/instrument/constants/__init__.py
emirdrp/instrument/tests/__init__.py
emirdrp/instrument/tests/dtuheader.py
emirdrp/instrument/tests/test_assembly.py
emirdrp/instrument/tests/test_config.py
emirdrp/instrument/tests/test_csuconf.py
pyemir-0.23.dist-info/licenses/AUTHORS.rst
pyemir-0.23.dist-info/licenses/LICENSE.txt
pyemir-0.23.dist-info/METADATA
pyemir-0.23.dist-info/WHEEL
pyemir-0.23.dist-info/entry_points.txt
pyemir-0.23.dist-info/top_level.txt
pyemir-0.23.dist-info/RECORD
