Metadata-Version: 2.4
Name: pyemir
Version: 0.23
Summary: EMIR Data Processing Pipeline
Author-email: Sergio Pascual <sergiopr@fis.ucm.es>, Nicolás Cardiel <cardiel@ucm.es>
License: GPL-3.0-or-later
Project-URL: Homepage, https://github.com/guaix-ucm/pyemir
Project-URL: Repository, https://github.com/guaix-ucm/pyemir.git
Project-URL: Documentation, https://pyemir.readthedocs.io/en/stable/
Classifier: Programming Language :: Python :: 3.10
Classifier: Programming Language :: Python :: 3.11
Classifier: Programming Language :: Python :: 3.12
Classifier: Programming Language :: Python :: 3.13
Classifier: Programming Language :: Python :: 3.14
Classifier: Development Status :: 3 - Alpha
Classifier: Environment :: Console
Classifier: Intended Audience :: Science/Research
Classifier: License :: OSI Approved :: GNU General Public License (GPL)
Classifier: Operating System :: OS Independent
Classifier: Topic :: Scientific/Engineering :: Astronomy
Requires-Python: >=3.10
License-File: LICENSE.txt
License-File: AUTHORS.rst
Requires-Dist: astropy
Requires-Dist: importlib_resources
Requires-Dist: lmfit
Requires-Dist: matplotlib
Requires-Dist: numpy
Requires-Dist: numina>=0.36.0
Requires-Dist: photutils>=1.4
Requires-Dist: reproject
Requires-Dist: sep>=1.4.0
Requires-Dist: scikit-image>=0.22
Requires-Dist: scikit-learn>=0.19
Requires-Dist: scipy>=1.8
Provides-Extra: test
Requires-Dist: pytest>=6; extra == "test"
Requires-Dist: pytest-remotedata; extra == "test"
Requires-Dist: hypothesis; extra == "test"
Provides-Extra: docs
Requires-Dist: sphinx>=7; extra == "docs"
Requires-Dist: sphinx_rtd_theme; extra == "docs"
Provides-Extra: tool
Requires-Dist: PyQt5; extra == "tool"
Dynamic: license-file
